tap_mssql/__init__.py
tap_mssql/connection.py
tap_mssql/sync_strategies/__init__.py
tap_mssql/sync_strategies/common.py
tap_mssql/sync_strategies/full_table.py
tap_mssql/sync_strategies/incremental.py
tap_mssql/sync_strategies/log_based.py
tap_mssql-2.6.5.dist-info/LICENSE
tap_mssql-2.6.5.dist-info/METADATA
tap_mssql-2.6.5.dist-info/WHEEL
tap_mssql-2.6.5.dist-info/entry_points.txt
tap_mssql-2.6.5.dist-info/RECORD
