Metadata-Version: 2.1
Name: tap-mssql
Version: 2.6.5
Summary: A pipelinewise compatible tap for connecting Microsoft SQL Server
Home-page: https://robertwinters.nl
License: GNU Affero
Keywords: singer,meltano,pipelinewise,mssql
Author: Rob Winters
Author-email: wintersrd@gmail.com
Requires-Python: >=3.8,<3.13
Classifier: Development Status :: 5 - Production/Stable
Classifier: License :: Other/Proprietary License
Classifier: Programming Language :: Python :: 3
Classifier: Programming Language :: Python :: 3.8
Classifier: Programming Language :: Python :: 3.9
Classifier: Programming Language :: Python :: 3.10
Classifier: Programming Language :: Python :: 3.11
Classifier: Programming Language :: Python :: 3.12
Classifier: Topic :: Database
Requires-Dist: attrs (>=24.2.0)
Requires-Dist: backoff (>=1.8.0)
Requires-Dist: pendulum (>=1.2.0)
Requires-Dist: pymssql (>=2.1.4,!=2.2.8)
Requires-Dist: realit-singer-python (>=5.0.0)
Project-URL: Repository, https://github.com/wintersrd/pipelinewise-tap-mssql
